<annotation>
  <folder>images</folder>
  <filename>file (259)</filename>
  <path>C:\Users\scharmann\Desktop\pi\ml-tweet-bot\images\file (259).jpg</path>
  <source>
    <database>Unknown</database>
  </source>
  <size>
    <width>360</width>
    <height>480</height>
    <depth>3</depth>
  </size>
  <segmented>0</segmented>
  <object>
    <name>basket</name>
    <pose>Unspecified</pose>
    <truncated>0</truncated>
    <difficult>0</difficult>
    <bndbox>
      <xmin>21</xmin>
      <ymin>2</ymin>
      <xmax>347</xmax>
      <ymax>416</ymax>
    </bndbox>
  </object>
</annotation>
